setup.py
django_sql_inspector.egg-info/PKG-INFO
django_sql_inspector.egg-info/SOURCES.txt
django_sql_inspector.egg-info/dependency_links.txt
django_sql_inspector.egg-info/requires.txt
django_sql_inspector.egg-info/top_level.txt
sql_inspector/__init__.py