Metadata-Version: 1.0
Name: django-sql-inspector
Version: 1.0.0
Summary: Analyze and measure the SQL calls, used by your Django application
Home-page: UNKNOWN
Author: Rory McCann
Author-email: rory@technomancy.org
License: GPLv3
Platform: UNKNOWN
